acestock/__init__.py
acestock/gateway.py
acestock/md.py
acestock/td.py
acestock-0.1.7.dist-info/LICENSE
acestock-0.1.7.dist-info/WHEEL
acestock-0.1.7.dist-info/METADATA
acestock-0.1.7.dist-info/RECORD
