Metadata-Version: 2.1
Name: acestock
Version: 0.1.7
Summary: A gateway for jonpy on A stock market.
License: MIT
Author: FangyangJz
Author-email: fangyang.jing@hotmail.com
Requires-Python: >=3.7.1,<4.0.0
Classifier: License :: OSI Approved :: MIT License
Classifier: Programming Language :: Python :: 3
Classifier: Programming Language :: Python :: 3.10
Classifier: Programming Language :: Python :: 3.8
Classifier: Programming Language :: Python :: 3.9
Requires-Dist: easytrader (>=0.23.0,<0.24.0)
Requires-Dist: jotdx (>=0.1.2,<0.2.0)
Requires-Dist: pandas (>=1.3.4,<2.0.0)
Requires-Dist: tzlocal (>=4.1,<5.0)
